{
"type": "FeatureCollection",
"name": "ubicacion_ceditvallejo",
"crs": { "type": "name", "properties": { "name": "urn:ogc:def:crs:OGC:1.3:CRS84" } },
"features": [
{ "type": "Feature", "properties": { "fid": 1, "nombre": "Centro de Desarrollo e Innovación Vallejo-i" }, "geometry": { "type": "Point", "coordinates": [ -99.181864752485566, 19.488166866133323 ] } }
]
}
